COPYING.txt
MANIFEST.in
README.txt
setup.py
nginxctl/__init__.py
nginxctl/__main__.py
nginxctl/nginxctl.py
nginxctl.egg-info/PKG-INFO
nginxctl.egg-info/SOURCES.txt
nginxctl.egg-info/dependency_links.txt
nginxctl.egg-info/entry_points.txt
nginxctl.egg-info/top_level.txt