Metadata-Version: 1.1
Name: nginxctl
Version: 1.1.1
Summary: This tool is similar to apachectl but for nginx. The                     important feature of this tool is ability to list vhosts                     configured on a nginx server
Home-page: https://github.com/fooltruth/nginxctl
Author: Alex Newton Alexander
Author-email: fooltruth1980@gmail.com
License: UNKNOWN
Platform: UNKNOWN
Classifier: Programming Language :: Python
Classifier: Programming Language :: Python :: 2
Classifier: License :: OSI Approved :: GNU General Public License (GPL)
Classifier: Environment :: Console
